google/rpc/status_pb2.py
google/rpc/error_details_pb2.py
google/api/httpbody_pb2.py
google/api/field_behavior_pb2.py
google/api/annotations_pb2.py
google/api/http_pb2.py
google/api/expr/v1alpha1/checked_pb2.py
google/api/expr/v1alpha1/value_pb2.py
google/api/expr/v1alpha1/syntax_pb2.py
google/api/expr/v1alpha1/explain_pb2.py
google/api/expr/v1alpha1/eval_pb2.py
pyprotoc_plugin/__init__.py
pyprotoc_plugin/plugins.py
pyprotoc_plugin/helpers.py
respect/logging.py
respect/py.typed
respect/grpc/options.py
kubernetes_utils/ownership.py
kubernetes_utils/retry.py
kubernetes_utils/custom_object.py
kubernetes_utils/api.py
kubernetes_utils/kubernetes_client.py
kubernetes_utils/helpers.py
kubernetes_utils/resources/role_bindings.py
kubernetes_utils/resources/nodes.py
kubernetes_utils/resources/pods.py
kubernetes_utils/resources/secrets.py
kubernetes_utils/resources/service_accounts.py
kubernetes_utils/resources/cluster_role_bindings.py
kubernetes_utils/resources/cluster_roles.py
kubernetes_utils/resources/custom_objects.py
kubernetes_utils/resources/services.py
kubernetes_utils/resources/roles.py
kubernetes_utils/resources/persistent_volume_claims.py
kubernetes_utils/resources/deployments.py
kubernetes_utils/resources/storage_classes.py
kubernetes_utils/resources/namespaces.py
kubernetes_utils/resources/custom_resource_definitions.py
validate/validate_pb2.py
opencensus/proto/trace/v1/trace_pb2.py
opencensus/proto/trace/v1/trace_config_pb2.py
opencensus/proto/resource/v1/resource_pb2.py
xds/annotations/v3/status_pb2.py
xds/annotations/v3/migrate_pb2.py
xds/annotations/v3/sensitive_pb2.py
xds/annotations/v3/security_pb2.py
xds/annotations/v3/versioning_pb2.py
xds/type/matcher/v3/matcher_pb2.py
xds/type/matcher/v3/domain_pb2.py
xds/type/matcher/v3/string_pb2.py
xds/type/matcher/v3/http_inputs_pb2.py
xds/type/matcher/v3/regex_pb2.py
xds/type/matcher/v3/ip_pb2.py
xds/type/matcher/v3/range_pb2.py
xds/type/matcher/v3/cel_pb2.py
reboot_dev_reboot-0.13.2.dist-info/entry_points.txt
reboot_dev_reboot-0.13.2.dist-info/RECORD
reboot_dev_reboot-0.13.2.dist-info/WHEEL
reboot_dev_reboot-0.13.2.dist-info/LICENSE
reboot_dev_reboot-0.13.2.dist-info/top_level.txt
reboot_dev_reboot-0.13.2.dist-info/METADATA
