Metadata-Version: 2.1
Name: reboot_dev_reboot
Version: 0.13.2
Summary: The Reboot library
Classifier: License :: OSI Approved :: Apache Software License
Classifier: Operating System :: POSIX :: Linux
Classifier: Programming Language :: Python :: 3
Requires-Python: >=3.10
License-File: LICENSE
Requires-Dist: aiofiles ==23.2.1
Requires-Dist: aiohttp ==3.10.5
Requires-Dist: colorama ==0.4.6
Requires-Dist: cryptography ==42.0.2
Requires-Dist: gitpython ==3.1.31
Requires-Dist: googleapis-common-protos ==1.61.0
Requires-Dist: grpc-interceptor ==0.15.4
Requires-Dist: grpcio ==1.56.2
Requires-Dist: grpcio-health-checking ==1.56.2
Requires-Dist: grpcio-reflection ==1.56.2
Requires-Dist: grpcio-status ==1.56.2
Requires-Dist: grpcio-tools ==1.56.2
Requires-Dist: jinja2 ==3.1.2
Requires-Dist: jinja2-strcase >=0.0.2
Requires-Dist: kubernetes-asyncio ==31.1.0
Requires-Dist: mypy-protobuf ==3.5.0
Requires-Dist: packaging ==23.1
Requires-Dist: pathspec ==0.12.1
Requires-Dist: protobuf ==4.25.2
Requires-Dist: psutil ==6.0.0
Requires-Dist: pyjwt >=2.8.0
Requires-Dist: pyprctl ==0.1.3
Requires-Dist: pyyaml ==6.0.2
Requires-Dist: typing-extensions ==4.9.0
Requires-Dist: urllib3 ==1.26.15
Requires-Dist: watchdog ==4.0.0
Requires-Dist: websockets >=12.0
Requires-Dist: uuid7 ==0.1.0
